pymboot.cpython-312-x86_64-linux-gnu.so
pymboot_rs/__init__.pyi
pymboot_rs/py.typed
pymboot_rs-0.2.0.data/scripts/rblhost
pymboot_rs.libs/libattr-4f2a9577.so.1.1.0
pymboot_rs.libs/libbz2-a273e504.so.1.0.6
pymboot_rs.libs/libcap-79733b59.so.2.22
pymboot_rs.libs/libdw-0-780627ce.176.so
pymboot_rs.libs/libelf-0-3d9de92a.176.so
pymboot_rs.libs/liblzma-004595ca.so.5.2.2
pymboot_rs.libs/libudev-1f672570.so.1.6.2
pymboot_rs.scripts/rblhost
pymboot_rs-0.2.0.dist-info/METADATA
pymboot_rs-0.2.0.dist-info/WHEEL
pymboot_rs-0.2.0.dist-info/top_level.txt
pymboot_rs-0.2.0.dist-info/RECORD
pymboot_rs-0.2.0.dist-info/licenses/LICENSE
