Metadata-Version: 2.4
Name: pymboot-rs
Version: 0.2.0
Summary: Python bindings for McuBoot implementation in Rust, providing high-performance communication with NXP MCU bootloader.
Author-email: NXP <spsdk@nxp.com>
License-Expression: BSD-3-Clause
Classifier: Programming Language :: Rust
Classifier: Programming Language :: Python :: Implementation :: CPython
Classifier: Programming Language :: Python :: Implementation :: PyPy
Requires-Python: >=3.9
License-File: LICENSE
Dynamic: license-file
